confutilPPP/__confutil__.py
confutilPPP/__init__.py
confutilPPP/__log__.py
lib/logPPP/__init__.py
confutilPPP-1.3.2.dist-info/METADATA
confutilPPP-1.3.2.dist-info/WHEEL
confutilPPP-1.3.2.dist-info/top_level.txt
confutilPPP-1.3.2.dist-info/RECORD
