Metadata-Version: 2.1
Name: confutilPPP
Version: 1.3.2
Summary: A simple configuration file tool
Home-page: https://github.com/Aurorax-own/confutilPPP
Author: Aurorax-own
Author-email: 15047150695@163.com
Project-URL: Source, https://github.com/Aurorax-own/confutilPPP
Project-URL: Tracker, https://github.com/Aurorax-own/confutilPPP/issues
Requires-Dist: pyyaml ==6.0.1
